reqcheck/__init__.py
reqcheck/cmdline.py
reqcheck/constraints.py
reqcheck/defines.py
reqcheck/exceptions.py
reqcheck/formatters.py
reqcheck/packages.py
reqcheck/versions.py
reqcheck-0.1.9.dist-info/LICENSE
reqcheck-0.1.9.dist-info/METADATA
reqcheck-0.1.9.dist-info/WHEEL
reqcheck-0.1.9.dist-info/entry_points.txt
reqcheck-0.1.9.dist-info/top_level.txt
reqcheck-0.1.9.dist-info/RECORD
