Metadata-Version: 2.1
Name: reqcheck
Version: 0.1.9
Summary: Compare installed Python package versions with PyPI
Home-page: https://github.com/jaleskovec/reqcheck
Author: Jozef Leskovec
Author-email: jozefleskovec@gmail.com
License: MIT
Keywords: requirements check compare installed virtualenv venv pypi package packages version versions
Platform: UNKNOWN
Classifier: Development Status :: 3 - Alpha
Classifier: Intended Audience :: Developers
Classifier: Topic :: Software Development :: Build Tools
Classifier: License :: OSI Approved :: MIT License
Classifier: Programming Language :: Python :: 2
Classifier: Programming Language :: Python :: 2.7
Classifier: Programming Language :: Python :: 3
Classifier: Programming Language :: Python :: 3.4
Classifier: Programming Language :: Python :: 3.5
Classifier: Programming Language :: Python :: 3.6
Classifier: Programming Language :: Python :: 3.7
Classifier: Programming Language :: Python :: 3.8
Classifier: Programming Language :: Python :: 3.9
Requires-Dist: requests
Requires-Dist: six
Requires-Dist: tabulate
